telguarder/__init__.py
telguarder/cli.py
telguarder/client.py
telguarder/const.py
telguarder/exceptions.py
telguarder/models.py
telguarder/py.typed
telguarder/version.py
telguarder-1.0.1.dist-info/LICENSE.md
telguarder-1.0.1.dist-info/METADATA
telguarder-1.0.1.dist-info/WHEEL
telguarder-1.0.1.dist-info/entry_points.txt
telguarder-1.0.1.dist-info/RECORD
