Metadata-Version: 2.1
Name: telguarder
Version: 1.0.1
Summary: An unofficial client library for using the telguarder API
Home-page: https://github.com/bendikrb/telguarder
License: MIT
Keywords: caller-id,api-client,unofficial
Author: Bendik R. Brenne
Author-email: bendik@konstant.no
Requires-Python: >=3.11,<4.0
Classifier: Environment :: Console
Classifier: Intended Audience :: Developers
Classifier: License :: OSI Approved :: MIT License
Classifier: Programming Language :: Python
Classifier: Programming Language :: Python :: 3
Classifier: Programming Language :: Python :: 3.11
Classifier: Programming Language :: Python :: 3.12
Classifier: Programming Language :: Python :: 3.13
Provides-Extra: doc
Provides-Extra: test
Requires-Dist: aiohttp (>=3.10.9,<4.0.0)
Requires-Dist: async-timeout (>=5.0.0,<6.0.0)
Requires-Dist: mashumaro (>=3.13.1,<4.0.0)
Requires-Dist: orjson (>=3.10.7,<4.0.0)
Requires-Dist: rich (>=13.9.2,<14.0.0)
Project-URL: Documentation, https://telguarder.readthedocs.io/en/latest/
Project-URL: Repository, https://github.com/bendikrb/telguarder
